{
  "products": [
    {
      "productImg": "https://i.ibb.co/vPxtCnJ/img1.jpg",
      "productName": "Black Joggers",
      "productPrice": 4500,
      "quantity": 2,
      "size": "XS",
      "parentId": 1,
      "id": 16
    },
    {
      "productImg": "https://i.ibb.co/jRG2yHW/img3.jpg",
      "productName": "Cream Cargo Pants",
      "productPrice": 4500,
      "quantity": 1,
      "size": "L",
      "parentId": 3,
      "id": 18
    },
    {
      "productImg": "https://i.ibb.co/ZzThSL1/img2.jpg",
      "productName": "White Shirts",
      "productPrice": 2500,
      "quantity": 1,
      "size": "L",
      "parentId": 2,
      "id": 19
    },
    {
      "productImg": "https://i.ibb.co/ZzThSL1/img2.jpg",
      "productName": "White Shirts",
      "productPrice": 2500,
      "quantity": 2,
      "size": "XS",
      "parentId": 2,
      "id": 20
    },
    {
      "productImg": "https://i.ibb.co/vPxtCnJ/img1.jpg",
      "productName": "Black Joggers",
      "productPrice": 4500,
      "quantity": 1,
      "size": "L",
      "parentId": 1,
      "id": 21
    },
    {
      "productImg": "https://i.ibb.co/vPxtCnJ/img1.jpg",
      "productName": "Black Joggers",
      "productPrice": 4500,
      "quantity": 4,
      "size": "M",
      "parentId": 1,
      "id": 22
    }
  ]
}